mavsdk/__init__.py
mavsdk/_base.py
mavsdk/action.py
mavsdk/action_pb2.py
mavsdk/action_pb2_grpc.py
mavsdk/action_server.py
mavsdk/action_server_pb2.py
mavsdk/action_server_pb2_grpc.py
mavsdk/arm_authorizer_server.py
mavsdk/arm_authorizer_server_pb2.py
mavsdk/arm_authorizer_server_pb2_grpc.py
mavsdk/async_plugin_manager.py
mavsdk/calibration.py
mavsdk/calibration_pb2.py
mavsdk/calibration_pb2_grpc.py
mavsdk/camera.py
mavsdk/camera_pb2.py
mavsdk/camera_pb2_grpc.py
mavsdk/camera_server.py
mavsdk/camera_server_pb2.py
mavsdk/camera_server_pb2_grpc.py
mavsdk/component_information.py
mavsdk/component_information_pb2.py
mavsdk/component_information_pb2_grpc.py
mavsdk/component_information_server.py
mavsdk/component_information_server_pb2.py
mavsdk/component_information_server_pb2_grpc.py
mavsdk/component_metadata.py
mavsdk/component_metadata_pb2.py
mavsdk/component_metadata_pb2_grpc.py
mavsdk/component_metadata_server.py
mavsdk/component_metadata_server_pb2.py
mavsdk/component_metadata_server_pb2_grpc.py
mavsdk/core.py
mavsdk/core_pb2.py
mavsdk/core_pb2_grpc.py
mavsdk/events.py
mavsdk/events_pb2.py
mavsdk/events_pb2_grpc.py
mavsdk/failure.py
mavsdk/failure_pb2.py
mavsdk/failure_pb2_grpc.py
mavsdk/follow_me.py
mavsdk/follow_me_pb2.py
mavsdk/follow_me_pb2_grpc.py
mavsdk/ftp.py
mavsdk/ftp_pb2.py
mavsdk/ftp_pb2_grpc.py
mavsdk/ftp_server.py
mavsdk/ftp_server_pb2.py
mavsdk/ftp_server_pb2_grpc.py
mavsdk/geofence.py
mavsdk/geofence_pb2.py
mavsdk/geofence_pb2_grpc.py
mavsdk/gimbal.py
mavsdk/gimbal_pb2.py
mavsdk/gimbal_pb2_grpc.py
mavsdk/gripper.py
mavsdk/gripper_pb2.py
mavsdk/gripper_pb2_grpc.py
mavsdk/info.py
mavsdk/info_pb2.py
mavsdk/info_pb2_grpc.py
mavsdk/log_files.py
mavsdk/log_files_pb2.py
mavsdk/log_files_pb2_grpc.py
mavsdk/log_streaming.py
mavsdk/log_streaming_pb2.py
mavsdk/log_streaming_pb2_grpc.py
mavsdk/manual_control.py
mavsdk/manual_control_pb2.py
mavsdk/manual_control_pb2_grpc.py
mavsdk/mavlink_direct.py
mavsdk/mavlink_direct_pb2.py
mavsdk/mavlink_direct_pb2_grpc.py
mavsdk-3.10.1.dist-info/LICENSE.txt
mavsdk-3.10.1.dist-info/METADATA
mavsdk-3.10.1.dist-info/WHEEL
mavsdk-3.10.1.dist-info/top_level.txt
mavsdk-3.10.1.dist-info/RECORD
