Metadata-Version: 2.1
Name: mavsdk
Version: 3.10.1
Summary: Python wrapper for MAVSDK
Home-page: https://github.com/mavlink/MAVSDK-Python
Maintainer: Jonas Vautherin, Julian Oes
Maintainer-email: jonas@auterion.com, julian.oes@auterion.com
License: UNKNOWN
Project-URL: Bug Reports, https://github.com/mavlink/MAVSDK-Python/issues
Project-URL: Source, https://github.com/mavlink/MAVSDK-Python/
Platform: UNKNOWN
Classifier: Development Status :: 5 - Production/Stable
Classifier: Intended Audience :: Developers
Classifier: License :: OSI Approved :: BSD License
Classifier: Programming Language :: Python :: 3.7
Requires-Python: >=3.7
License-File: LICENSE.txt
Requires-Dist: grpcio (>=1.64.1)
Requires-Dist: protobuf (>=5.27.1)
